{
    "version": "https://jsonfeed.org/version/1",
    "title": "地底太阳",
    "subtitle": "一个微电子东方众的祈祷",
    "icon": "https://subterranean-sun.github.io/images/favicon.ico",
    "description": "",
    "home_page_url": "https://subterranean-sun.github.io",
    "items": [
        {
            "id": "https://subterranean-sun.github.io/Solid-state_physics/",
            "url": "https://subterranean-sun.github.io/Solid-state_physics/",
            "title": "晶体衍射与倒格子作业1",
            "date_published": "2022-10-27T14:49:34.095Z",
            "content_html": "<img src = \"Solid-state_physics.png\">",
            "tags": [
                "大二的稀烂笔记",
                "固体物理"
            ]
        }
    ]
}